ammoo/__init__.py
ammoo/_utils.py
ammoo/channel.py
ammoo/channel_id_manager.py
ammoo/closeable_queue.py
ammoo/connect.py
ammoo/connection.py
ammoo/consumer.py
ammoo/message.py
ammoo/validatation.py
ammoo/version.py
ammoo/auth/__init__.py
ammoo/auth/abc.py
ammoo/auth/password.py
ammoo/auth/mechanisms/__init__.py
ammoo/auth/mechanisms/amqplain.py
ammoo/auth/mechanisms/sasl_plain.py
ammoo/exceptions/__init__.py
ammoo/exceptions/channel.py
ammoo/exceptions/connection.py
ammoo/exceptions/consumer.py
ammoo/wire/__init__.py
ammoo/wire/class_and_method.py
ammoo/wire/classes.py
ammoo/wire/constants.py
ammoo/wire/methods.py
ammoo/wire/typing.py
ammoo/wire/frames/__init__.py
ammoo/wire/frames/body.py
ammoo/wire/frames/header.py
ammoo/wire/frames/heartbeat.py
ammoo/wire/frames/method/__init__.py
ammoo/wire/frames/method/basic.py
ammoo/wire/frames/method/channel.py
ammoo/wire/frames/method/confirm.py
ammoo/wire/frames/method/connection.py
ammoo/wire/frames/method/exchange.py
ammoo/wire/frames/method/queue.py
ammoo/wire/low/__init__.py
ammoo/wire/low/containers.py
ammoo/wire/low/exceptions.py
ammoo/wire/low/misc.py
ammoo/wire/low/peer_properties.py
ammoo/wire/low/strings.py
ammoo/wire/low/structs.py
ammoo-0.2.1.dist-info/DESCRIPTION.rst
ammoo-0.2.1.dist-info/LICENSE.txt
ammoo-0.2.1.dist-info/METADATA
ammoo-0.2.1.dist-info/RECORD
ammoo-0.2.1.dist-info/WHEEL
ammoo-0.2.1.dist-info/metadata.json
ammoo-0.2.1.dist-info/top_level.txt
